pyextrasafe/__init__.py
pyextrasafe/__init__.pyi
pyextrasafe/py.typed
pyextrasafe/_pyextrasafe.pypy39-pp73-x86_64-linux-gnu.so
pyextrasafe/_pyextrasafe.pyi
pyextrasafe-0.1.0a1.dist-info/LICENSE.md
pyextrasafe-0.1.0a1.dist-info/RECORD
pyextrasafe-0.1.0a1.dist-info/WHEEL
pyextrasafe-0.1.0a1.dist-info/METADATA
pyextrasafe-0.1.0a1.dist-info/top_level.txt
