Metadata-Version: 2.1
Name: pyextrasafe
Version: 0.1.0a1
Summary: Make your code extrasafe by preventing it from calling unneeded syscalls
Home-page: https://github.com/Kijewski/pyextrasafe
Author: René Kijewski
Author-email: pypi.org@k6i.de
License: MIT License
Project-URL: Changelog, https://github.com/Kijewski/pyextrasafe/blob/main/CHANGELOG.md
Project-URL: Code, https://github.com/Kijewski/pyextrasafe
Project-URL: Documentation, https://pyextrasafe.readthedocs.io/
Project-URL: Download, https://pypi.org/project/pyextrasafe/
Project-URL: Homepage, https://github.com/Kijewski/pyextrasafe
Project-URL: Tracker, https://github.com/Kijewski/pyextrasafe/issues
Classifier: License :: OSI Approved :: Apache Software License
Classifier: Development Status :: 3 - Alpha
Classifier: Programming Language :: Rust
Classifier: Operating System :: POSIX :: Linux
Classifier: Intended Audience :: Developers
Classifier: Programming Language :: Python :: 3
Classifier: Programming Language :: Python :: 3 :: Only
Classifier: Programming Language :: Python :: 3.7
Classifier: Programming Language :: Python :: 3.8
Classifier: Programming Language :: Python :: 3.9
Classifier: Programming Language :: Python :: 3.10
Classifier: Programming Language :: Python :: 3.11
Requires-Python: <4,>=3.7
License-File: LICENSE.md
